swarmauri_tokens_composite/__init__.py
swarmauri_tokens_composite-0.3.0.dev4.dist-info/LICENSE
swarmauri_tokens_composite-0.3.0.dev4.dist-info/METADATA
swarmauri_tokens_composite-0.3.0.dev4.dist-info/WHEEL
swarmauri_tokens_composite-0.3.0.dev4.dist-info/entry_points.txt
swarmauri_tokens_composite-0.3.0.dev4.dist-info/RECORD
